TRExt-0.2.1.dist-info/DESCRIPTION.rst
TRExt-0.2.1.dist-info/METADATA
TRExt-0.2.1.dist-info/RECORD
TRExt-0.2.1.dist-info/WHEEL
TRExt-0.2.1.dist-info/metadata.json
TRExt-0.2.1.dist-info/top_level.txt
trext/__init__.py
trext/api.py
trext/db/__init__.py
trext/db/conn.py
trext/db/consume.py
trext/db/fill.py
trext/db/typemap.py
trext/db/utils.py
trext/extract/__init__.py
trext/extract/build.py
trext/extract/exceptions.py
trext/extract/server.py
trext/extract/utils.py
