Metadata-Version: 2.0
Name: TRExt
Version: 0.2.1
Summary: TRExt - Tableau Refresh Extract (Externally)
Home-page: https://github.com/AtheonAnalytics/trext
Author: Vathsala Achar
Author-email: vathsala@atheon.co.uk
License: MIT
Platform: UNKNOWN
Classifier: Development Status :: 3 - Alpha
Classifier: Intended Audience :: Developers
Classifier: License :: OSI Approved :: MIT License
Classifier: Natural Language :: English
Classifier: Programming Language :: Python :: 2.7
Requires-Dist: pyodbc
Requires-Dist: mock
